check_ezproxy/__init__.py
check_ezproxy/__main__.py
check_ezproxy/args.py
check_ezproxy/check_ezproxy.py
check_ezproxy/checks.py
check_ezproxy/config.py
check_ezproxy/config_template.py
check_ezproxy/errors.py
check_ezproxy/get_config.py
check_ezproxy/kb.py
check_ezproxy/places.py
check_ezproxy/registration.py
check_ezproxy-0.1.1.dist-info/DESCRIPTION.rst
check_ezproxy-0.1.1.dist-info/METADATA
check_ezproxy-0.1.1.dist-info/RECORD
check_ezproxy-0.1.1.dist-info/WHEEL
check_ezproxy-0.1.1.dist-info/entry_points.txt
check_ezproxy-0.1.1.dist-info/metadata.json
check_ezproxy-0.1.1.dist-info/top_level.txt
