Metadata-Version: 2.0
Name: check-ezproxy
Version: 0.1.1
Summary: Command line tool to test EZProxy stanza configurations and link health.
Home-page: https://github.com/chill17/check_ezproxy/
Author: Ed Hill
Author-email: hill.charles2@gmail.com
License: MIT
Platform: UNKNOWN
Classifier: Development Status :: 4 - Beta
Classifier: License :: OSI Approved :: MIT License
Classifier: Programming Language :: Python :: 2
Classifier: Programming Language :: Python :: 2.7
Classifier: Programming Language :: Python :: 3
Classifier: Programming Language :: Python :: 3.3
Classifier: Programming Language :: Python :: 3.4
Classifier: Programming Language :: Python :: 3.5
Requires-Dist: gevent
Requires-Dist: pykbart
Requires-Dist: requests
